odoo8_addon_auth_admin_passkey-8.0.2.1.1.99.dev19-py2.7-nspkg.pth
odoo8_addon_auth_admin_passkey-8.0.2.1.1.99.dev19.dist-info/DESCRIPTION.rst
odoo8_addon_auth_admin_passkey-8.0.2.1.1.99.dev19.dist-info/METADATA
odoo8_addon_auth_admin_passkey-8.0.2.1.1.99.dev19.dist-info/RECORD
odoo8_addon_auth_admin_passkey-8.0.2.1.1.99.dev19.dist-info/WHEEL
odoo8_addon_auth_admin_passkey-8.0.2.1.1.99.dev19.dist-info/metadata.json
odoo8_addon_auth_admin_passkey-8.0.2.1.1.99.dev19.dist-info/namespace_packages.txt
odoo8_addon_auth_admin_passkey-8.0.2.1.1.99.dev19.dist-info/top_level.txt
odoo_addons/auth_admin_passkey/README.rst
odoo_addons/auth_admin_passkey/__init__.py
odoo_addons/auth_admin_passkey/__openerp__.py
odoo_addons/auth_admin_passkey/data/ir_config_parameter.xml
odoo_addons/auth_admin_passkey/i18n/ar.po
odoo_addons/auth_admin_passkey/i18n/auth_admin_passkey.pot
odoo_addons/auth_admin_passkey/i18n/ca.po
odoo_addons/auth_admin_passkey/i18n/da.po
odoo_addons/auth_admin_passkey/i18n/de.po
odoo_addons/auth_admin_passkey/i18n/el_GR.po
odoo_addons/auth_admin_passkey/i18n/es.po
odoo_addons/auth_admin_passkey/i18n/es_ES.po
odoo_addons/auth_admin_passkey/i18n/fi.po
odoo_addons/auth_admin_passkey/i18n/fr.po
odoo_addons/auth_admin_passkey/i18n/fr_CH.po
odoo_addons/auth_admin_passkey/i18n/hr.po
odoo_addons/auth_admin_passkey/i18n/hr_HR.po
odoo_addons/auth_admin_passkey/i18n/it.po
odoo_addons/auth_admin_passkey/i18n/nl.po
odoo_addons/auth_admin_passkey/i18n/pt_BR.po
odoo_addons/auth_admin_passkey/i18n/sl.po
odoo_addons/auth_admin_passkey/i18n/tr.po
odoo_addons/auth_admin_passkey/i18n/tr_TR.po
odoo_addons/auth_admin_passkey/i18n/zh_CN.po
odoo_addons/auth_admin_passkey/models/__init__.py
odoo_addons/auth_admin_passkey/models/res_config.py
odoo_addons/auth_admin_passkey/models/res_users.py
odoo_addons/auth_admin_passkey/static/description/icon.png
odoo_addons/auth_admin_passkey/tests/__init__.py
odoo_addons/auth_admin_passkey/tests/test_auth_admin_passkey.py
odoo_addons/auth_admin_passkey/views/res_config_view.xml
